odoo/addons/sale_order_default_carrier/LICENSE
odoo/addons/sale_order_default_carrier/README.rst
odoo/addons/sale_order_default_carrier/__init__.py
odoo/addons/sale_order_default_carrier/__manifest__.py
odoo/addons/sale_order_default_carrier/i18n/de_CH.po
odoo/addons/sale_order_default_carrier/images/screen.png
odoo/addons/sale_order_default_carrier/models/__init__.py
odoo/addons/sale_order_default_carrier/models/sale_order.py
odoo/addons/sale_order_default_carrier/static/description/icon.png
odoo/addons/sale_order_default_carrier/static/description/index.html
odoo/addons/sale_order_default_carrier/tests/TEST_INSTRUCTIONS.rst
odoo/addons/sale_order_default_carrier/views/sale_order.xml
odoo_addon_sale_order_default_carrier-16.0.1.0.0.dist-info/METADATA
odoo_addon_sale_order_default_carrier-16.0.1.0.0.dist-info/WHEEL
odoo_addon_sale_order_default_carrier-16.0.1.0.0.dist-info/top_level.txt
odoo_addon_sale_order_default_carrier-16.0.1.0.0.dist-info/RECORD
